CONTRIBUTING.md
Dockerfile
LICENSE
README.md
codecov.yml
requirements.txt
setup.py
.circleci/config.yml
nway/__init__.py
nway/diagnostics.py
nway/image_processing_utils.py
nway/meta_registration.py
nway/nway_matching.py
nway/pairwise_matching.py
nway/schemas.py
nway/transforms.py
nway/utils.py
ophys_nway_matching.egg-info/PKG-INFO
ophys_nway_matching.egg-info/SOURCES.txt
ophys_nway_matching.egg-info/dependency_links.txt
ophys_nway_matching.egg-info/requires.txt
ophys_nway_matching.egg-info/top_level.txt
test/test_diagnostics.py
test/test_image_processing_utils.py
test/test_meta_registration.py
test/test_nway.py
test/test_pairwise.py
test/test_transforms.py
test/test_utils.py
test/test_files/test0/input.json
test/test_files/test0/matching_result.txt
test/test_files/test0/new_output.json
test/test_files/test0/table_before_pruning.json
test/test_files/test0/specimen_722884882/ophys_session_775289198/ophys_experiment_775614751/processed/ophys_cell_segmentation_run_775777590/avgInt_a1X.png
test/test_files/test0/specimen_722884882/ophys_session_775289198/ophys_experiment_775614751/processed/ophys_cell_segmentation_run_775777590/maxInt_masks.tif
test/test_files/test0/specimen_722884882/ophys_session_778015591/ophys_experiment_778644591/processed/ophys_cell_segmentation_run_780871038/avgInt_a1X.png
test/test_files/test0/specimen_722884882/ophys_session_778015591/ophys_experiment_778644591/processed/ophys_cell_segmentation_run_780871038/maxInt_masks.tif
test/test_files/test0/specimen_722884882/ophys_session_787661032/ophys_experiment_788490510/processed/ophys_cell_segmentation_run_789282590/avgInt_a1X.png
test/test_files/test0/specimen_722884882/ophys_session_787661032/ophys_experiment_788490510/processed/ophys_cell_segmentation_run_789282590/maxInt_masks.tif
test/test_files/test0/specimen_722884882/ophys_session_789746168/ophys_experiment_790146945/processed/ophys_cell_segmentation_run_790612585/avgInt_a1X.png
test/test_files/test0/specimen_722884882/ophys_session_789746168/ophys_experiment_790146945/processed/ophys_cell_segmentation_run_790612585/maxInt_masks.tif
