Metadata-Version: 1.0
Name: ophys-nway-matching
Version: 0.5.1
Summary: building up a repo from the ophys_ophys_nway running in LIMS, Aug 2019
Home-page: https://github.com/AllenInstitute/ophys_nway_matching
Author: Daniel Kapner, original code Fuhui Long
Author-email: danielk@alleninstitute.org
License: UNKNOWN
Platform: UNKNOWN
